webscrapper_/__init__.py
webscrapperpy-0.1.0.dist-info/METADATA
webscrapperpy-0.1.0.dist-info/WHEEL
webscrapperpy-0.1.0.dist-info/top_level.txt
webscrapperpy-0.1.0.dist-info/RECORD
