Metadata-Version: 2.1
Name: webscrapperpy
Version: 0.1.0
Summary: Simple Python module to fetch webpage contents via https://r.jina.ai/{URL}
Home-page: https://github.com/yourusername/webscrapper_
Author: Your Name
Author-email: Your Name <you@example.com>
License: MIT
Project-URL: Homepage, https://github.com/yourusername/webscrapper_
Classifier: Programming Language :: Python :: 3
Classifier: Operating System :: OS Independent
Requires-Python: >=3.8
Requires-Dist: requests>=2.0.0
